sparc.config-1.2.3-py3.7-nspkg.pth
sparc/config/__init__.py
sparc/config/configure.zcml
sparc/config/container.py
sparc/config/container.txt
sparc/config/ftesting.zcml
sparc/config/interfaces.py
sparc/config/mapping.py
sparc/config/mapping.txt
sparc/config/sequence.py
sparc/config/sequence.txt
sparc/config/testing.py
sparc/config/verify.py
sparc/config/verify.txt
sparc/config/tests/__init__.py
sparc/config/tests/test_container.py
sparc/config/tests/test_mapping.py
sparc/config/tests/test_sequence.py
sparc/config/tests/test_verify.py
sparc/config/yaml/__init__.py
sparc/config/yaml/configure.zcml
sparc/config/yaml/documents.py
sparc/config/yaml/documents.txt
sparc/config/yaml/interfaces.py
sparc/config/yaml/tests/__init__.py
sparc/config/yaml/tests/test_documents.py
sparc.config-1.2.3.dist-info/LICENSE.txt
sparc.config-1.2.3.dist-info/METADATA
sparc.config-1.2.3.dist-info/WHEEL
sparc.config-1.2.3.dist-info/entry_points.txt
sparc.config-1.2.3.dist-info/namespace_packages.txt
sparc.config-1.2.3.dist-info/top_level.txt
sparc.config-1.2.3.dist-info/RECORD
